{
      "basepokemons": [
            {
                  "name": "You",
                  "hp": 5,
                  "atk": 1,
                  "dif": 1,
                  "satk": 1,
                  "sdif": 1,
                  "maxlvl": 1000,
                  "unlocked": 0,
                  "lvl": 0,
                  "phys": 0,
                  "magic": 0,
                  "special": 0
            },
            {
                  "name": "Coco",
                  "hp": 5,
                  "atk": 1,
                  "dif": 1,
                  "satk": 1,
                  "sdif": 1,
                  "maxlvl": 1000,
                  "unlocked": 0,
                  "lvl": 0,
                  "phys": 0,
                  "magic": 0,
                  "special": 0
            }
      ],
      "party": [
            {
                  "name": "You",
                  "hp": 5,
                  "atk": 1,
                  "dif": 1,
                  "satk": 1,
                  "sdif": 1,
                  "maxlvl": 1000,
                  "unlocked": 0,
                  "lvl": 0,
                  "phys": 0,
                  "magic": 0,
                  "special": 0
            },
            {
                  "name": "Bird",
                  "hp": 91.2,
                  "atk": 100.8,
                  "dif": 91.2,
                  "satk": 96,
                  "sdif": 100.8,
                  "maxlvl": 12,
                  "unlocked": 0,
                  "lvl": 0,
                  "phys": 0,
                  "magic": 0,
                  "special": 0
            }
      ],
      "reserve": [
            {
                  "name": "Goblin",
                  "hp": 150,
                  "atk": 105,
                  "dif": 126,
                  "satk": 105,
                  "sdif": 114,
                  "maxlvl": 15,
                  "unlocked": 0,
                  "lvl": 0,
                  "phys": 0,
                  "magic": 0,
                  "special": 0
            },
            {
                  "name": "Snake",
                  "hp": 133,
                  "atk": 171,
                  "dif": 144.4,
                  "satk": 152,
                  "sdif": 159.6,
                  "maxlvl": 19,
                  "unlocked": 0,
                  "lvl": 0,
                  "phys": 0,
                  "magic": 0,
                  "special": 0
            },
            {
                  "name": "You1",
                  "hp": 5,
                  "atk": 1,
                  "dif": 1,
                  "satk": 1,
                  "sdif": 1,
                  "maxlvl": 1000,
                  "unlocked": 0,
                  "lvl": 0,
                  "phys": 0,
                  "magic": 0,
                  "special": 0
            },
            {
                  "name": "You3",
                  "hp": 5,
                  "atk": 1,
                  "dif": 1,
                  "satk": 1,
                  "sdif": 1,
                  "maxlvl": 1000,
                  "unlocked": 0,
                  "lvl": 0,
                  "phys": 0,
                  "magic": 0,
                  "special": 0
            },
            {
                  "name": "You4",
                  "hp": 5,
                  "atk": 1,
                  "dif": 1,
                  "satk": 1,
                  "sdif": 1,
                  "maxlvl": 1000,
                  "unlocked": 0,
                  "lvl": 0,
                  "phys": 0,
                  "magic": 0,
                  "special": 0
            },
            {
                  "name": "Slime",
                  "hp": 80,
                  "atk": 80,
                  "dif": 80,
                  "satk": 80,
                  "sdif": 80,
                  "maxlvl": 10,
                  "unlocked": 0,
                  "lvl": 0,
                  "phys": 0,
                  "magic": 0,
                  "special": 0
            }
      ],
      "loopactionvisibility": [
            true,
            true
      ]
}